postfix/__init__.py
postfix/postfix.py
tests/__init__.py
tests/code_to_be_tested.py
tests/test_postfix.py
postfix-0.0.5.dist-info/LICENSE
postfix-0.0.5.dist-info/METADATA
postfix-0.0.5.dist-info/WHEEL
postfix-0.0.5.dist-info/top_level.txt
postfix-0.0.5.dist-info/RECORD
