Metadata-Version: 2.1
Name: postfix
Version: 0.0.5
Summary: A Python package to facilitate writing tests for a testless code base.
Home-page: https://github.com/matthias-baer/postfix
Author: Matthias Baer
Author-email: matthias.baer@mpl.mpg.de
License: MIT
Platform: ALL
Classifier: Operating System :: OS Independent
Classifier: Programming Language :: Python :: 3
Requires-Python: >=3.6
License-File: LICENSE
